ti.me-0.3.6.dist-info/METADATA
ti.me-0.3.6.dist-info/RECORD
ti.me-0.3.6.dist-info/WHEEL
ti.me-0.3.6.dist-info/entry_points.txt
ti.me-0.3.6.dist-info/top_level.txt
timecli/__init__.py
timecli/cli.py
timecli/config.py
timecli/handling.py
timecli/logging.py
timecli/parsing.py
timecli/utils.py
timecli/views.py
timelib/__init__.py
timelib/exceptions.py
timelib/logging.py
timelib/management.py
timelib/models/__init__.py
timelib/models/associations.py
timelib/models/base.py
timelib/models/plan.py
timelib/models/planned_task.py
timelib/models/task.py
